tylTools.py
tyl_tools.py
tyl-2.0.dist-info/METADATA
tyl-2.0.dist-info/WHEEL
tyl-2.0.dist-info/top_level.txt
tyl-2.0.dist-info/RECORD
