Metadata-Version: 2.1
Name: tyl
Version: 2.0
Summary: A  module for test
Author: tyl
Author-email: 2371527712@qq.com
License: MIT
